hd_active/__init__.py
hd_active/hd_action_state.py
hd_active/hd_active.ini
hd_active/hd_active.py
hd_active/hd_active_config.py
hd_active/main.py
hd_active/utils.py
hd_active/ui/__init__.py
hd_active/ui/log_dialog.py
hd_active/ui/settings_dialog.py
hd_active/ui/system_tray_icon.py
hd_active/ui/forms/__init__.py
hd_active/ui/forms/resources_rc.py
hd_active/ui/forms/ui_log_dialog.py
hd_active/ui/forms/ui_settings_dialog.py
hd_active-0.1.1.dist-info/entry_points.txt
hd_active-0.1.1.dist-info/LICENSE.txt
hd_active-0.1.1.dist-info/WHEEL
hd_active-0.1.1.dist-info/METADATA
hd_active-0.1.1.dist-info/RECORD
