Metadata-Version: 2.1
Name: hd_active
Version: 0.1.1
Summary: Prevent external HDs from becoming inactive (sleeping).
Author: Joao Coelho
Classifier: License :: OSI Approved :: MIT License
Requires-Dist: pyside6
Project-URL: Documentation, https://joaonc.github.io/hd_active
Project-URL: Home, https://github.com/joaonc/hd_active
